galaxy/__init__.py
galaxy/py.typed
galaxy/tool_util_models/__init__.py
galaxy/tool_util_models/_types.py
galaxy/tool_util_models/assertions.py
galaxy/tool_util_models/dynamic_tool_models.py
galaxy/tool_util_models/parameter_validators.py
galaxy/tool_util_models/parameters.py
galaxy/tool_util_models/tool_outputs.py
galaxy/tool_util_models/tool_source.py
galaxy_tool_util_models-25.0.3.dist-info/licenses/LICENSE
galaxy_tool_util_models-25.0.3.dist-info/METADATA
galaxy_tool_util_models-25.0.3.dist-info/WHEEL
galaxy_tool_util_models-25.0.3.dist-info/top_level.txt
galaxy_tool_util_models-25.0.3.dist-info/RECORD
